{
  "city_key": "santiago_centro",
  "city_label": "Santiago, Chile",
  "timezone_name": "America/Santiago",
  "country": "Chile",
  "zone_name": "Santiago Centro",
  "location_name": "pedestrian_axis",
  "latitude": -33.43771966560363,
  "longitude": -70.64692495103672,
  "altitude_m": 106,
  "gps_accuracy_m": 8.1,
  "heading_deg": 294,
  "speed_kmh": 0.5,
  "status": "resting",
  "phase": "overnight",
  "local_time_str": "00:23",
  "signal": "stable",
  "updated_utc": "2026-06-24 04:23:05 UTC"
}