{
  "city_key": "santiago_centro",
  "city_label": "Santiago, Chile",
  "timezone_name": "America/Santiago",
  "country": "Chile",
  "zone_name": "Santiago Centro",
  "location_name": "urban_sector",
  "latitude": -33.444196155747065,
  "longitude": -70.65114031655683,
  "altitude_m": 99,
  "gps_accuracy_m": 5.9,
  "heading_deg": 334,
  "speed_kmh": 0.6,
  "status": "stationary",
  "phase": "morning",
  "local_time_str": "08:53",
  "signal": "nominal",
  "updated_utc": "2026-07-04 12:53:32 UTC"
}