{
  "city_key": "santiago_centro",
  "city_label": "Santiago, Chile",
  "timezone_name": "America/Santiago",
  "country": "Chile",
  "zone_name": "Santiago Centro",
  "location_name": "pedestrian_axis",
  "latitude": -33.437736565696575,
  "longitude": -70.64678800522717,
  "altitude_m": 124,
  "gps_accuracy_m": 6.9,
  "heading_deg": 285,
  "speed_kmh": 0.8,
  "status": "in_transit",
  "phase": "early_morning",
  "local_time_str": "06:10",
  "signal": "stable",
  "updated_utc": "2026-04-04 09:10:14 UTC"
}