{
  "city_key": "santiago_centro",
  "city_label": "Santiago, Chile",
  "timezone_name": "America/Santiago",
  "country": "Chile",
  "zone_name": "Santiago Centro",
  "location_name": "residential_sector",
  "latitude": -33.44184982084106,
  "longitude": -70.6543263706825,
  "altitude_m": 106,
  "gps_accuracy_m": 4.2,
  "heading_deg": 67,
  "speed_kmh": 8.9,
  "status": "walking",
  "phase": "morning",
  "local_time_str": "08:05",
  "signal": "nominal",
  "updated_utc": "2026-04-12 12:05:32 UTC"
}