{
  "city_key": "santiago_centro",
  "city_label": "Santiago, Chile",
  "timezone_name": "America/Santiago",
  "country": "Chile",
  "zone_name": "Santiago Centro",
  "location_name": "transit_corridor",
  "latitude": -33.44640327159423,
  "longitude": -70.66144483489579,
  "altitude_m": 98,
  "gps_accuracy_m": 8.4,
  "heading_deg": 204,
  "speed_kmh": 0.2,
  "status": "stationary",
  "phase": "early_morning",
  "local_time_str": "06:21",
  "signal": "stable",
  "updated_utc": "2026-05-27 10:21:33 UTC"
}